pyos/__init__.py
pymintkit-0.0.1.dist-info/METADATA
pymintkit-0.0.1.dist-info/WHEEL
pymintkit-0.0.1.dist-info/license.txt
pymintkit-0.0.1.dist-info/top_level.txt
pymintkit-0.0.1.dist-info/RECORD
