Metadata-Version: 2.1
Name: pymintkit
Version: 0.0.1
Summary: A small package on OS College Project
Author: Sikandar Bhide
License: UNKNOWN
Platform: UNKNOWN
Requires-Python: >=3.6
License-File: license.txt
